spkit/__init__.py
spkit/pylfsr.py
spkit/utils.py
spkit/core/__init__.py
spkit/core/advance_techniques.py
spkit/core/decomposition.py
spkit/core/fractional_processes.py
spkit/core/information_theory.py
spkit/core/information_theory_advance.py
spkit/core/processing.py
spkit/core/ramanujan_methods.py
spkit/cwt/__init__.py
spkit/cwt/cwt_fn.py
spkit/data/__init__.py
spkit/data/dataGen.py
spkit/data/load_data.py
spkit/data/files/EEG16SecData.pkl
spkit/data/files/EEG16sec_artifact.pkl
spkit/data/files/ecg_3samples_12leads.pkl
spkit/data/files/ecg_egm_smaple_28s.pkl
spkit/data/files/ecg_sample_1_12leads.pkl
spkit/data/files/ecg_sample_2_12leads.pkl
spkit/data/files/ecg_sample_3_12leads.pkl
spkit/data/files/gsr_samples.pkl
spkit/data/files/optical_bio_samples.pkl
spkit/data/files/optical_rabbit_samples.pkl
spkit/data/files/ppg_samples.pkl
spkit/data/files/primitive_polynomials_GF2_dict.txt
spkit/eeg/__init__.py
spkit/eeg/artifact_correction.py
spkit/eeg/atar_algorithm.py
spkit/eeg/eeg_map.py
spkit/eeg/eeg_processing.py
spkit/eeg/files/Standard_1005.csv
spkit/eeg/files/Standard_1005.elc.txt
spkit/eeg/files/Standard_1010_MI.csv
spkit/eeg/files/Standard_1010_MI.png
spkit/eeg/files/Standard_1020.csv
spkit/eeg/files/Standard_1020_spkit.csv
spkit/eeg/files/precomputed_projections.pkl
spkit/geometry/__init__.py
spkit/geometry/basic_geo.py
spkit/geometry/geomagic.py
spkit/io/__init__.py
spkit/io/io_utils.py
spkit/mea/__init__.py
spkit/mea/mea_processing.py
spkit/ml/Logistic.py
spkit/ml/Probabilistic.py
spkit/ml/Trees.py
spkit/ml/__init__.py
spkit/stats/__init__.py
spkit/stats/stats_fun.py
spkit/text/__init__.py
spkit/text/text_processing.py
spkit/utils_misc/__init__.py
spkit/utils_misc/borrowed.py
spkit/utils_misc/io_utils.py
spkit/utils_misc/tf_utils.py
spkit/utils_misc/utils.py
spkit-0.0.9.7.dist-info/LICENSE
spkit-0.0.9.7.dist-info/METADATA
spkit-0.0.9.7.dist-info/WHEEL
spkit-0.0.9.7.dist-info/top_level.txt
spkit-0.0.9.7.dist-info/RECORD
