Metadata-Version: 2.1
Name: spkit
Version: 0.0.9.7
Summary: SpKit: Signal Processing ToolKit
Home-page: https://spkit.github.io
Download-URL: https://github.com/Nikeshbajaj/spkit/tarball/0.0.9.7
Author: Nikesh Bajaj
Author-email: nikkeshbajaj@gmail.com
Maintainer: Nikesh Bajaj
Maintainer-email: nikkeshbajaj@gmail.com
License: MIT
Project-URL: Documentation, https://spkit.readthedocs.io/
Project-URL: Say Thanks!, https://github.com/Nikeshbajaj
Project-URL: Source, https://github.com/Nikeshbajaj/spkit
Project-URL: Tracker, https://github.com/Nikeshbajaj/spkit/issues
Keywords: Signal processing machine-learning entropy Rényi Kullback–Leibler divergence mutual information decision-tree logistic-regression naive-bayes LFSR ICA EEG-signal-processing ATAR
Platform: any
Classifier: Programming Language :: Python :: 3
Classifier: Programming Language :: Python :: 3.5
Classifier: Programming Language :: Python :: 3.6
Classifier: Programming Language :: Python :: 3.7
Classifier: Natural Language :: English
Classifier: License :: OSI Approved :: MIT License
Classifier: Operating System :: OS Independent
Classifier: Development Status :: 5 - Production/Stable
Classifier: Topic :: Scientific/Engineering :: Artificial Intelligence
Classifier: Topic :: Scientific/Engineering :: Information Analysis
Classifier: Topic :: Software Development :: Libraries :: Python Modules
Classifier: Topic :: Multimedia
Classifier: Topic :: Multimedia :: Sound/Audio :: Analysis
Classifier: Topic :: Multimedia :: Sound/Audio :: Speech
Classifier: Topic :: Scientific/Engineering :: Image Processing
Classifier: Topic :: Scientific/Engineering :: Visualization
Classifier: Intended Audience :: Developers
Classifier: Intended Audience :: Science/Research
Classifier: Intended Audience :: Education
Classifier: Development Status :: 5 - Production/Stable
Requires-Python: >=3.5
License-File: LICENSE
Requires-Dist: numpy >1.8
Requires-Dist: pandas
Requires-Dist: scipy
Requires-Dist: scikit-learn
Requires-Dist: python-picard
Requires-Dist: matplotlib
Requires-Dist: PyWavelets
Requires-Dist: pylfsr
Requires-Dist: h5py
Requires-Dist: seaborn
Requires-Dist: joblib
Requires-Dist: phyaat
